rtl/relu_quantizer.v
`timescale 1ns/1ps
// ReLU and saturation block. Internal sum is shifted back to Q4.4 format.
module relu_quantizer #(
    parameter ACC_WIDTH = 24,
    parameter OUT_WIDTH = 8,
    parameter FRAC_BITS = 4
)(
    input  wire signed [ACC_WIDTH-1:0] acc_in,
    output reg  signed [OUT_WIDTH-1:0] data_out
);
    localparam signed [OUT_WIDTH-1:0] MAX_VAL =  8'sd127;
    localparam signed [OUT_WIDTH-1:0] MIN_VAL =  8'sd0;
    wire signed [ACC_WIDTH-1:0] shifted = acc_in >>> FRAC_BITS;
    always @(*) begin
        if (shifted <= 0)
            data_out = MIN_VAL;
        else if (shifted > MAX_VAL)
            data_out = MAX_VAL;
        else
            data_out = shifted[OUT_WIDTH-1:0];
    end
endmodule

rtl/mac_unit.v
`timescale 1ns/1ps
// Signed fixed-point MAC unit for CNN convolution accelerator.
module mac_unit #(
    parameter DATA_WIDTH = 8,
    parameter COEFF_WIDTH = 8,
    parameter ACC_WIDTH = 24
)(
    input  wire signed [DATA_WIDTH-1:0]  pixel,
    input  wire signed [COEFF_WIDTH-1:0] weight,
    input  wire signed [ACC_WIDTH-1:0]   acc_in,
    output wire signed [ACC_WIDTH-1:0]   acc_out
);
    wire signed [DATA_WIDTH+COEFF_WIDTH-1:0] product;
    assign product = pixel * weight;
    assign acc_out = acc_in + {{(ACC_WIDTH-(DATA_WIDTH+COEFF_WIDTH)){product[DATA_WIDTH+COEFF_WIDTH-1]}}, product};
endmodule

rtl/conv3x3_core.v
`timescale 1ns/1ps
// 3x3 CNN convolution core with nine parallel multipliers and registered output.
// Input/weight data are signed Q4.4 fixed-point values.
module conv3x3_core #(
    parameter DATA_WIDTH = 8,
    parameter COEFF_WIDTH = 8,
    parameter ACC_WIDTH = 24,
    parameter FRAC_BITS = 4
)(
    input  wire clk,
    input  wire rst_n,
    input  wire valid_in,
    input  wire signed [DATA_WIDTH-1:0]  p00, p01, p02,
    input  wire signed [DATA_WIDTH-1:0]  p10, p11, p12,
    input  wire signed [DATA_WIDTH-1:0]  p20, p21, p22,
    input  wire signed [COEFF_WIDTH-1:0] w00, w01, w02,
    input  wire signed [COEFF_WIDTH-1:0] w10, w11, w12,
    input  wire signed [COEFF_WIDTH-1:0] w20, w21, w22,
    input  wire signed [ACC_WIDTH-1:0]   bias,
    output reg valid_out,
    output reg signed [DATA_WIDTH-1:0] data_out,
    output reg signed [ACC_WIDTH-1:0] acc_debug
);
    wire signed [ACC_WIDTH-1:0] s0,s1,s2,s3,s4,s5,s6,s7,s8;
    mac_unit #(.DATA_WIDTH(DATA_WIDTH),.COEFF_WIDTH(COEFF_WIDTH),.ACC_WIDTH(ACC_WIDTH)) m0(p00,w00,bias,s0);
    mac_unit #(.DATA_WIDTH(DATA_WIDTH),.COEFF_WIDTH(COEFF_WIDTH),.ACC_WIDTH(ACC_WIDTH)) m1(p01,w01,s0,s1);
    mac_unit #(.DATA_WIDTH(DATA_WIDTH),.COEFF_WIDTH(COEFF_WIDTH),.ACC_WIDTH(ACC_WIDTH)) m2(p02,w02,s1,s2);
    mac_unit #(.DATA_WIDTH(DATA_WIDTH),.COEFF_WIDTH(COEFF_WIDTH),.ACC_WIDTH(ACC_WIDTH)) m3(p10,w10,s2,s3);
    mac_unit #(.DATA_WIDTH(DATA_WIDTH),.COEFF_WIDTH(COEFF_WIDTH),.ACC_WIDTH(ACC_WIDTH)) m4(p11,w11,s3,s4);
    mac_unit #(.DATA_WIDTH(DATA_WIDTH),.COEFF_WIDTH(COEFF_WIDTH),.ACC_WIDTH(ACC_WIDTH)) m5(p12,w12,s4,s5);
    mac_unit #(.DATA_WIDTH(DATA_WIDTH),.COEFF_WIDTH(COEFF_WIDTH),.ACC_WIDTH(ACC_WIDTH)) m6(p20,w20,s5,s6);
    mac_unit #(.DATA_WIDTH(DATA_WIDTH),.COEFF_WIDTH(COEFF_WIDTH),.ACC_WIDTH(ACC_WIDTH)) m7(p21,w21,s6,s7);
    mac_unit #(.DATA_WIDTH(DATA_WIDTH),.COEFF_WIDTH(COEFF_WIDTH),.ACC_WIDTH(ACC_WIDTH)) m8(p22,w22,s7,s8);

    wire signed [DATA_WIDTH-1:0] q_out;
    relu_quantizer #(.ACC_WIDTH(ACC_WIDTH),.OUT_WIDTH(DATA_WIDTH),.FRAC_BITS(FRAC_BITS)) q0(.acc_in(s8),.data_out(q_out));

    always @(posedge clk or negedge rst_n) begin
        if (!rst_n) begin
            valid_out <= 1'b0;
            data_out <= 0;
            acc_debug <= 0;
        end else begin
            valid_out <= valid_in;
            if (valid_in) begin
                data_out <= q_out;
                acc_debug <= s8;
            end
        end
    end
endmodule

testbench/tb_conv3x3_core.v
`timescale 1ns/1ps
module tb_conv3x3_core;
    reg clk; reg rst_n; reg valid_in;
    reg signed [7:0] p00,p01,p02,p10,p11,p12,p20,p21,p22;
    reg signed [7:0] w00,w01,w02,w10,w11,w12,w20,w21,w22;
    reg signed [23:0] bias;
    wire valid_out; wire signed [7:0] data_out; wire signed [23:0] acc_debug;

    conv3x3_core dut(
        .clk(clk), .rst_n(rst_n), .valid_in(valid_in),
        .p00(p00),.p01(p01),.p02(p02),.p10(p10),.p11(p11),.p12(p12),.p20(p20),.p21(p21),.p22(p22),
        .w00(w00),.w01(w01),.w02(w02),.w10(w10),.w11(w11),.w12(w12),.w20(w20),.w21(w21),.w22(w22),
        .bias(bias), .valid_out(valid_out), .data_out(data_out), .acc_debug(acc_debug)
    );

    always #5 clk = ~clk; // 100 MHz clock

    task apply_window;
        input signed [7:0] a0,a1,a2,a3,a4,a5,a6,a7,a8;
        begin
            @(negedge clk);
            p00=a0; p01=a1; p02=a2; p10=a3; p11=a4; p12=a5; p20=a6; p21=a7; p22=a8;
            valid_in=1'b1;
        end
    endtask

    initial begin
        $dumpfile("waveforms/vcd/conv3x3_core.vcd");
        $dumpvars(0,tb_conv3x3_core);
        clk=0; rst_n=0; valid_in=0; bias=0;
        // Sobel-like edge kernel in Q4.4: [-1 0 1; -2 0 2; -1 0 1]
        w00=-16; w01=0; w02=16; w10=-32; w11=0; w12=32; w20=-16; w21=0; w22=16;
        p00=0;p01=0;p02=0;p10=0;p11=0;p12=0;p20=0;p21=0;p22=0;
        repeat(3) @(negedge clk); rst_n=1;
        apply_window(8, 12, 20, 8, 12, 20, 8, 12, 20);
        apply_window(16,16,16,16,16,16,16,16,16);
        apply_window(32,24,16,32,24,16,32,24,16);
        apply_window(0,16,32,0,16,32,0,16,32);
        @(negedge clk); valid_in=0;
        repeat(6) @(negedge clk);
        $finish;
    end
endmodule

waveforms/vcd/conv3x3_core.vcd
$date
    Advanced VLSI CNN project generated waveform
$end
$version
    Educational VCD for conv3x3_core
$end
$timescale 1ns $end
$scope module tb_conv3x3_core $end
$var wire 1 ! clk $end
$var wire 1 " rst_n $end
$var wire 1 # valid_in $end
$var wire 1 $ valid_out $end
$var wire 8 % data_out [7:0] $end
$var wire 24 & acc_debug [23:0] $end
$upscope $end
$enddefinitions $end
#0
0!
0"
0#
0$
b00000000 %
b000000000000000000000000 &
#5
1!
#10
0!
#15
1!
#20
0!
#25
1!
1"
#30
0!
#35
1!
1#
#40
0!
#45
1!
1$
b00110000 %
b000000000000001100000000 &
#50
0!
#55
1!
b00000000 %
b000000000000000000000000 &
#60
0!
#65
1!
b00000000 %
b111111111111110100000000 &
#70
0!
#75
1!
0#
b01100000 %
b000000000000011000000000 &
#80
0!
#85
1!
0$
